BUGS
MANIFEST.in
README.rst
batchfile.example
matplotlibrc.dist
netperf-wrapper
netperf-wrapper-mime.xml
netperf-wrapper.desktop
netperf-wrapperrc.example
setup.py
man/netperf-wrapper.1
misc/ditg-control-server.py
misc/ditg-ignore-client-log.patch
misc/iperf-server.py
misc/iperf_unix_timestamps.patch
misc/tcpdump-wrapper.py
misc/test-exec.sh
misc/testcontrol-web-service.py
netperf_wrapper/__init__.py
netperf_wrapper/aggregators.py
netperf_wrapper/batch.py
netperf_wrapper/build_info.py
netperf_wrapper/error_ellipse.py
netperf_wrapper/formatters.py
netperf_wrapper/gui.py
netperf_wrapper/metadata.py
netperf_wrapper/ordereddict.py
netperf_wrapper/resultset.py
netperf_wrapper/runners.py
netperf_wrapper/settings.py
netperf_wrapper/testenv.py
netperf_wrapper/transformers.py
netperf_wrapper/util.py
netperf_wrapper.egg-info/PKG-INFO
netperf_wrapper.egg-info/SOURCES.txt
netperf_wrapper.egg-info/dependency_links.txt
netperf_wrapper.egg-info/top_level.txt
tests/bursts.conf
tests/cisco_5tcpup.conf
tests/cisco_5tcpup_2udpflood.conf
tests/cubic_ledbat.conf
tests/cubic_ledbat_1.conf
tests/cubic_reno.conf
tests/cubic_westwood.conf
tests/http-1up.conf
tests/http-rrul.conf
tests/http.conf
tests/iterated_bidirectional.conf
tests/ledbat_cubic_1.conf
tests/netperf_definitions.inc
tests/ping.conf
tests/reno_cubic_westwood_ledbat.conf
tests/reno_cubic_westwood_lp.conf
tests/rrul.conf
tests/rrul46.conf
tests/rrul46compete.conf
tests/rrul_50_up.conf
tests/rrul_be.conf
tests/rrul_icmp.conf
tests/rrul_noclassification.conf
tests/rrul_prio.conf
tests/rrul_torrent.conf
tests/rtt_fair.conf
tests/rtt_fair4be.conf
tests/rtt_fair6be.conf
tests/rtt_fair_up.conf
tests/sctp_vs_tcp.conf
tests/tcp_1down.conf
tests/tcp_1up.conf
tests/tcp_1up_noping.conf
tests/tcp_2up_delay.conf
tests/tcp_2up_square.conf
tests/tcp_2up_square_westwood.conf
tests/tcp_bidirectional.conf
tests/tcp_download.conf
tests/tcp_upload.conf
tests/tcp_upload_prio.conf
tests/udp_flood.conf
tests/voip-1up.conf
tests/voip-rrul.conf
tests/voip.conf
ui/mainwindow.ui
ui/resultwidget.ui