Metadata-Version: 1.0
Name: netperf-wrapper
Version: 0.9.1
Summary: Wrapper for running network tests such as netperf concurrently
Home-page: https://github.com/tohojo/netperf-wrapper
Author: Toke Høiland-Jørgensen <toke@toke.dk>
Author-email: toke@toke.dk
License: GNU GPLv3
Platform: Linux
